simpleip/__init__.py
simpleip/get.py
simpleip-0.3.1b0.dist-info/LICENSE
simpleip-0.3.1b0.dist-info/METADATA
simpleip-0.3.1b0.dist-info/WHEEL
simpleip-0.3.1b0.dist-info/top_level.txt
simpleip-0.3.1b0.dist-info/RECORD
