Metadata-Version: 2.1
Name: simpleip
Version: 0.3.1b0
Summary: A simple IP grabber for useful purposes
Home-page: https://github.com/KiaWeb/py-simple-ip
Author: KiasWorld
Author-email: lyly272003@gmail.com
License: UNKNOWN
Project-URL: Bug Tracker, https://github.com/KiaWeb/py-simple-ip/issues
Platform: UNKNOWN
Classifier: Programming Language :: Python :: 3
Classifier: License :: OSI Approved :: MIT License
Classifier: Operating System :: OS Independent
Requires-Python: >=3.10
License-File: LICENSE
